README.txt
TODO.txt
setup.cfg
setup.py
collective/__init__.py
collective.xdv.egg-info/PKG-INFO
collective.xdv.egg-info/SOURCES.txt
collective.xdv.egg-info/dependency_links.txt
collective.xdv.egg-info/entry_points.txt
collective.xdv.egg-info/namespace_packages.txt
collective.xdv.egg-info/not-zip-safe
collective.xdv.egg-info/requires.txt
collective.xdv.egg-info/top_level.txt
collective/xdv/__init__.py
collective/xdv/browser.py
collective/xdv/configure.zcml
collective/xdv/header.py
collective/xdv/icon.gif
collective/xdv/interfaces.py
collective/xdv/transform.py
collective/xdv/utils.py
collective/xdv/locales/collective.xdv.pot
collective/xdv/locales/ja/LC_MESSAGES/collective.xdv.po
collective/xdv/profiles/default/browserlayer.xml
collective/xdv/profiles/default/controlpanel.xml
collective/xdv/profiles/default/metadata.xml
collective/xdv/profiles/default/registry.xml
collective/xdv/tests/__init__.py
collective/xdv/tests/includes.html
collective/xdv/tests/includes.xml
collective/xdv/tests/one.html
collective/xdv/tests/othertheme.html
collective/xdv/tests/rules.xml
collective/xdv/tests/test_transform.py
collective/xdv/tests/theme.html
collective/xdv/tests/two.html
docs/HISTORY.txt
docs/INSTALL.txt
docs/LICENSE.GPL
docs/LICENSE.txt