Metadata-Version: 1.0
Name: collective.xdv
Version: 1.0rc11
Summary: Integrates the xdv Deliverance implementation with Plone using a post-publication hook to transform content
Home-page: http://pypi.python.org/pypi/collective.xdv
Author: Martin Aspeli
Author-email: optilude@gmail.com
License: GPL
Keywords: plone xdv deliverance theme transform xslt
Platform: UNKNOWN
Classifier: Framework :: Plone
Classifier: Programming Language :: Python
Classifier: Topic :: Software Development :: Libraries :: Python Modules
